{
    "cta": {
        "viewDocs": "Documentation",
        "github": "GitHub",
        "getStarted": "Commencer",
        "learnMore": "En savoir plus"
    },
    "site": {
        "tagline": "CMS base fichiers",
        "name": "Quicksite"
    },
    "home": {
        "welcomeMessage": "Un CMS PHP moderne base sur JSON avec une API REST puissante. Parfait pour les landing pages, portfolios et microsites.",
        "title": "Creez des sites rapidement.",
        "hero": {
            "title": "QuickSite",
            "subtitle": "Créez et gérez vos sites web entièrement via une API REST. Aucun framework frontend requis.",
            "cta_start": "Commencer",
            "cta_docs": "Voir la doc"
        },
        "features": {
            "title": "Fonctionnalités",
            "api": {
                "title": "Contrôle API Total",
                "desc": "Plus de 45 commandes pour gérer tous les aspects de votre site - routes, pages, styles, traductions, assets, et plus."
            },
            "i18n": {
                "title": "Multi-Langues",
                "desc": "Internationalisation intégrée avec détection automatique de la langue et gestion facile des traductions."
            },
            "css": {
                "title": "Style Dynamique",
                "desc": "Modifiez les variables CSS, règles et animations à la volée. Aucune étape de build requise."
            },
            "build": {
                "title": "Déploiement en Un Clic",
                "desc": "Générez des builds prêts pour la production avec PHP compilé, configs nettoyées et packaging ZIP."
            }
        },
        "stats": {
            "commands": "Commandes API",
            "api": "100% API",
            "dependencies": "Dépendances"
        }
    },
    "page": {
        "titles": {
            "about": "A propos - Quicksite",
            "features": "Fonctionnalites - Quicksite",
            "home": "QuickSite - Créez des sites web par API",
            "docs": "Documentation - QuickSite",
            "get-started": "Commencer - QuickSite",
            "privacy": "Politique de confidentialité - QuickSite",
            "terms": "Conditions d'utilisation - QuickSite",
            "404": "Page non trouvée - QuickSite",
            "guides": "Guides - QuickSite"
        }
    },
    "footer": {
        "madeWith": "Fait avec amour pour les developpeurs",
        "language": "Langue :",
        "terms": "Conditions d'utilisation",
        "privacy": "Politique de confidentialité",
        "copyright": "© 2025 QuickSite. Fait avec ❤️ et des APIs."
    },
    "404": {
        "message": "Désolé, la page que vous recherchez n'existe pas ou a été déplacée.",
        "backHome": "Retour à l'Accueil",
        "pageNotFound": "Page Non Trouvée"
    },
    "menu": {
        "about": "A propos",
        "features": "Fonctionnalites",
        "terms": "Conditions",
        "home": "Accueil",
        "docs": "Documentation",
        "getstarted": "Commencer",
        "github": "GitHub",
        "guides": "Guides"
    },
    "privacy": {
        "title": "Politique de confidentialite",
        "content": "Ceci est la politique de confidentialite de notre site web. Nous respectons votre vie privee."
    },
    "termOfUse": {
        "title": "Conditions d utilisation",
        "content": "Ce sont les conditions d utilisation de notre site web. En utilisant notre site, vous acceptez ces conditions."
    },
    "docs": {
        "title": "Documentation API",
        "intro": "Référence complète de toutes les commandes de gestion QuickSite. Tous les endpoints nécessitent une authentification.",
        "auth": {
            "title": "Authentification",
            "desc": "Incluez votre token API dans l'en-tête Authorization pour toutes les requêtes :"
        },
        "cat": {
            "folder": "Gestion des Dossiers",
            "route": "Gestion des Routes",
            "structure": "Gestion de la Structure",
            "alias": "Alias d'URL",
            "translation": "Gestion des Traductions",
            "language": "Gestion des Langues",
            "asset": "Gestion des Assets",
            "style": "Gestion des Styles",
            "css_vars": "Variables & Règles CSS",
            "animations": "Animations CSS",
            "customize": "Personnalisation du Site",
            "build": "Build & Déploiement",
            "auth": "Gestion des Tokens",
            "docs": "Documentation"
        }
    },
    "tutorial": {
        "title": "Premiers Pas avec QuickSite",
        "intro": "Suivez ce guide étape par étape pour configurer votre premier projet QuickSite en quelques minutes.",
        "step1": {
            "title": "1. Installer les Prérequis",
            "desc": "Assurez-vous d'avoir PHP 7.4+ (testé jusqu'à 8.4) et un serveur web (Apache, Nginx, ou WAMP/XAMPP) installés sur votre système."
        },
        "step2": {
            "title": "2. Cloner le Dépôt",
            "desc": "Clonez le dépôt du template QuickSite depuis GitHub et configurez votre serveur web pour pointer vers le dossier public."
        },
        "step3": {
            "title": "3. Configurer Votre Site",
            "desc": "Modifiez les fichiers de configuration dans le dossier secure/config pour définir le nom du site, les langues et le token API."
        },
        "step4": {
            "title": "4. Créer Votre Première Route",
            "desc": "Utilisez la commande API addRoute pour créer une nouvelle page, puis ajoutez du contenu avec la commande editStructure."
        },
        "step5": {
            "title": "5. Build & Déploiement",
            "desc": "Générez un build statique de votre site avec la commande build, puis uploadez les fichiers chez votre hébergeur."
        },
        "next": {
            "title": "Étapes Suivantes",
            "desc": "Maintenant que votre site fonctionne, explorez plus de fonctionnalités :",
            "docs": "Lisez la documentation API complète",
            "github": "Mettez-nous une étoile sur GitHub"
        }
    },
    "guides": {
        "title": "Guides Pratiques",
        "intro": "Apprenez QuickSite à travers des tutoriels orientés tâches. Chaque guide couvre des commandes API liées dans des workflows réels.",
        "toc": {
            "title": "Table des Matières",
            "pages": "Créer des Pages",
            "structure": "Édition de Structure",
            "i18n": "Internationalisation",
            "css": "CSS & Thèmes",
            "assets": "Assets & Branding",
            "urls": "Gestion des URLs",
            "deploy": "Déploiement",
            "security": "Sécurité API",
            "docs": "Documentation"
        },
        "pages": {
            "title": "Créer des Pages",
            "intro": "Créez, listez et supprimez des pages dans votre projet QuickSite. Chaque page consiste en un handler PHP et un fichier de structure JSON.",
            "create": {
                "desc": "Utilisez addRoute pour créer une nouvelle page. Cela crée le fichier PHP et le fichier de structure JSON.",
                "result": "Cela crée une nouvelle page à /about-us avec une structure JSON vide prête pour le contenu."
            },
            "list": {
                "desc": "Affichez toutes les pages de votre projet avec leurs métadonnées, incluant les routes et emplacements de fichiers."
            },
            "delete": {
                "desc": "Supprimez complètement une page. Cela supprime le handler PHP et le fichier de structure JSON."
            }
        },
        "structure": {
            "title": "Édition de Structure",
            "intro": "Maîtrisez le système de structure de page basé sur JSON. Chaque élément est un nœud avec tag, params et children.",
            "json": {
                "desc": "Les pages QuickSite sont définies comme des arbres JSON. Chaque nœud a un tag (élément HTML), des params optionnels (attributs), et des children (éléments imbriqués ou texte)."
            },
            "showids": {
                "desc": "Utilisez showIds pour voir les identifiants de nœuds pour l'édition chirurgicale. Chaque nœud obtient un ID en notation pointée comme 0.2.1 pour un ciblage précis."
            },
            "nodeid": {
                "desc": "Ciblez des nœuds spécifiques pour les mises à jour en utilisant leur nodeId. Cela permet des éditions précises sans remplacer toute la structure."
            },
            "actions": {
                "desc": "Utilisez les actions pour insérer, supprimer ou déplacer des nœuds par rapport aux autres. insertAfter, insertBefore et delete vous donnent un contrôle total."
            }
        },
        "i18n": {
            "title": "Internationalisation",
            "intro": "Construisez des sites multilingues avec des clés de traduction. QuickSite supporte plusieurs langues avec des structures de page partagées.",
            "add": {
                "desc": "Ajoutez ou mettez à jour des clés de traduction en toute sécurité. setTranslationKeys effectue une fusion profonde, donc les clés existantes sont préservées."
            },
            "health": {
                "desc": "Vérifiez la complétude des traductions dans toutes les langues. Trouvez les clés manquantes, les traductions non utilisées et obtenez des recommandations."
            },
            "newlang": {
                "desc": "Ajoutez une nouvelle langue à votre site. Cela crée le fichier de traduction et enregistre la langue dans la config."
            }
        },
        "css": {
            "title": "CSS & Thèmes",
            "intro": "Contrôlez l'apparence de votre site via l'API. Gérez les variables CSS, les règles et les animations de manière programmatique.",
            "variables": {
                "desc": "Les variables CSS (propriétés personnalisées) sont définies dans :root et peuvent être changées instantanément sur tout votre site."
            },
            "rules": {
                "desc": "Ajoutez ou mettez à jour des règles CSS pour n'importe quel sélecteur. Les styles sont fournis comme paires clé-valeur et fusionnés avec les règles existantes."
            },
            "animations": {
                "desc": "Créez des animations CSS keyframe qui peuvent être appliquées aux éléments en utilisant la propriété animation."
            }
        },
        "assets": {
            "title": "Assets & Branding",
            "intro": "Gérez les fichiers média et éléments de marque. Uploadez des images, polices et autres assets via l'API.",
            "upload": {
                "desc": "Uploadez des fichiers vers des dossiers catégorisés. Supporte les images, scripts, polices, audio et fichiers vidéo."
            },
            "favicon": {
                "desc": "Définissez le favicon du site depuis une image uploadée. L'image devrait être carrée (idéalement 32x32 ou plus)."
            },
            "pagetitle": {
                "desc": "Mettez à jour les titres de page par langue. Les titres apparaissent dans l'onglet du navigateur et les résultats de recherche."
            }
        },
        "urls": {
            "title": "Gestion des URLs",
            "intro": "Créez des alias d'URL et des redirections. Mappez plusieurs URLs vers le même contenu ou redirigez les anciennes URLs.",
            "redirect": {
                "desc": "Créez des mappings d'URL avec deux types : redirect (redirection HTTP 301) ou internal (routage transparent)."
            }
        },
        "deploy": {
            "title": "Déploiement",
            "intro": "Buildez et déployez votre site. Créez des builds de production optimisés avec des noms de dossiers personnalisables.",
            "build": {
                "desc": "Créez un build de production horodaté. Personnalisez les noms de dossiers public et secure pour votre environnement d'hébergement."
            },
            "space": {
                "desc": "Configurez le préfixe d'URL pour les sites tournant dans un sous-répertoire. Met à jour tous les liens internes automatiquement."
            }
        },
        "security": {
            "title": "Sécurité API",
            "intro": "Gérez l'accès API avec des tokens. Créez, listez et révoquez des tokens avec des permissions personnalisables.",
            "create": {
                "desc": "Générez de nouveaux tokens API avec des permissions spécifiques. Utilisez * pour l'accès complet ou read pour l'accès en lecture seule."
            },
            "manage": {
                "desc": "Affichez les tokens existants (valeurs masquées pour la sécurité) et révoquez les tokens qui ne sont plus nécessaires."
            }
        },
        "docs": {
            "title": "Documentation API",
            "intro": "Accédez à l'aide intégrée pour tous les endpoints API. La commande help fournit une documentation détaillée.",
            "help": {
                "desc": "Obtenez une documentation complète pour toutes les commandes ou une aide détaillée pour un endpoint spécifique."
            }
        },
        "footer": {
            "title": "Prêt à Construire ?",
            "desc": "Explorez la référence API complète ou consultez le code source sur GitHub.",
            "api": "Référence API",
            "github": "Voir sur GitHub"
        }
    }
}